bores/__init__.py
bores/_precision.py
bores/analyses.py
bores/boundary_conditions.py
bores/capillary_pressures.py
bores/cells.py
bores/config.py
bores/constants.py
bores/errors.py
bores/factories.py
bores/fractures.py
bores/models.py
bores/relperm.py
bores/simulate.py
bores/timing.py
bores/types.py
bores/utils.py
bores/diffusivity/__init__.py
bores/diffusivity/base.py
bores/diffusivity/explicit/__init__.py
bores/diffusivity/explicit/pressure.py
bores/diffusivity/explicit/saturation.py
bores/diffusivity/implicit/__init__.py
bores/diffusivity/implicit/full.py
bores/diffusivity/implicit/jacobian.py
bores/diffusivity/implicit/pressure.py
bores/grids/__init__.py
bores/grids/base.py
bores/grids/boundary_conditions.py
bores/grids/pvt.py
bores/grids/rock_fluid.py
bores/grids/saturation.py
bores/grids/updates.py
bores/pvt/__init__.py
bores/pvt/arrays.py
bores/pvt/core.py
bores/pvt/tables.py
bores/states/__init__.py
bores/states/base.py
bores/states/stores.py
bores/states/streams.py
bores/visualization/__init__.py
bores/visualization/base.py
bores/visualization/plotly1d.py
bores/visualization/plotly2d.py
bores/visualization/plotly3d.py
bores/wells/__init__.py
bores/wells/base.py
bores/wells/controls.py
bores/wells/core.py
bores_framework-0.0.1a1.dist-info/licenses/LICENSE
bores_framework-0.0.1a1.dist-info/METADATA
bores_framework-0.0.1a1.dist-info/WHEEL
bores_framework-0.0.1a1.dist-info/top_level.txt
bores_framework-0.0.1a1.dist-info/RECORD
