Metadata-Version: 2.4
Name: bores-framework
Version: 0.0.1a1
Summary: 3D 3-Phase Black-Oil Reservoir Modelling and Simulation Framework (BORES).
Author-email: ti-oluwa <tioluwa.dev@gmail.com>
License:                     GNU AFFERO GENERAL PUBLIC LICENSE
Requires-Python: >=3.10
License-File: LICENSE
Requires-Dist: attrs>=25.3.0
Requires-Dist: coolprop>=6.8.0
Requires-Dist: imageio>=2.37.0
Requires-Dist: intel-cmplr-lib-rt>=2025.3.1; sys_platform != "darwin"
Requires-Dist: ipython>=8.37.0
Requires-Dist: kaleido>=1.0.0
Requires-Dist: numba>=0.63.0
Requires-Dist: plotly>=6.2.0
Requires-Dist: pyamg>=5.3.0
Requires-Dist: scikit-image>=0.25.2
Requires-Dist: thermo>=0.4.2
Requires-Dist: trame>=3.12.0
Requires-Dist: typing-extensions>=4.15.0
Requires-Dist: numpy>=2.0.0; sys_platform != "darwin" and platform_machine == "x86_64"
Requires-Dist: scipy>=1.13.0; sys_platform != "darwin" and platform_machine == "x86_64"
Requires-Dist: numpy>=2.0.0; sys_platform == "darwin" or platform_machine != "x86_64"
Requires-Dist: scipy>=1.13.0; sys_platform == "darwin" or platform_machine != "x86_64"
Requires-Dist: cachetools>=6.2.4
Requires-Dist: h5py>=3.15.1
Requires-Dist: zarr>=2.18.3
Provides-Extra: dev
Requires-Dist: auto-mix-prep>=0.2.0; extra == "dev"
Requires-Dist: marimo>=0.18.4; extra == "dev"
Requires-Dist: mypy>=1.16.1; extra == "dev"
Requires-Dist: rich>=14.0.0; extra == "dev"
Requires-Dist: ruff>=0.12.1; extra == "dev"
Requires-Dist: ty>=0.0.1a26; extra == "dev"
Requires-Dist: watchdog>=6.0.0; extra == "dev"
Dynamic: license-file
